Workbook

Sheet Input Mask
A1: SaaS Financial Model – Input Assumptions
A2: Driver / Assumption | B2: Unit | C2: Source | D2: Year 1 | E2: Year 2 | F2: YoY Change | G2: Notes
A3: ── REVENUE DRIVERS ──
A4: Starting Customers | B4: # | C4: Assumption | D4: 50 | E4: 60 | F4: =IFERROR((E4-D4)/ABS(D4),"-") -> 0.2 | G4: Seed customers at start of year
A5: New Customers Added | B5: # | C5: Sales plan | D5: 120 | E5: 180 | F5: =IFERROR((E5-D5)/ABS(D5),"-") -> 0.5 | G5: Net new logos signed
A6: Churned Customers | B6: # | C6: Historical avg | D6: 10 | E6: 15 | F6: =IFERROR((E6-D6)/ABS(D6),"-") -> 0.5 | G6: Customers lost during year
A7: Avg ARR per Customer (New) | B7: $ | C7: Pricing model | D7: 24000 | E7: 28000 | F7: =IFERROR((E7-D7)/ABS(D7),"-") -> 0.16666667 | G7: Annual contract value, new logos
A8: Avg ARR per Customer (Existing) | B8: $ | C8: Pricing model | D8: 22000 | E8: 25000 | F8: =IFERROR((E8-D8)/ABS(D8),"-") -> 0.13636364 | G8: Blended existing book
A9: Expansion MRR % of ARR | B9: % | C9: Historical | D9: 0.05 | E9: 0.07 | F9: =IFERROR((E9-D9)/ABS(D9),"-") -> 0.4 | G9: Upsell & cross-sell rate
A10: Gross Churn Rate (Revenue) | B10: % | C10: Historical | D10: 0.08 | E10: 0.07 | F10: =IFERROR((E10-D10)/ABS(D10),"-") -> -0.125 | G10: % ARR lost from churn
A11: Net Revenue Retention | B11: % | C11: Calculated | D11: =1-D10+D9 -> 0.97 | E11: =1-E10+E9 -> 1 | F11: =IFERROR((E11-D11)/ABS(D11),"-") -> 0.030927835 | G11: NRR = 1 - Churn + Expansion
A12: ── COGS ASSUMPTIONS ──
A13: Hosting / DevOps (% of Revenue) | B13: % | C13: AWS invoices | D13: 0.08 | E13: 0.07 | F13: =IFERROR((E13-D13)/ABS(D13),"-") -> -0.125 | G13: Infrastructure costs
A14: Technical Support Headcount | B14: # | C14: Headcount plan | D14: 5 | E14: 8 | F14: =IFERROR((E14-D14)/ABS(D14),"-") -> 0.6 | G14: FTEs in support
A15: Avg Support Staff Cost | B15: $ | C15: HR / comp bands | D15: 75000 | E15: 78000 | F15: =IFERROR((E15-D15)/ABS(D15),"-") -> 0.04 | G15: Fully loaded annual cost
A16: Professional Services Margin | B16: % | C16: P&L history | D16: 0.2 | E16: 0.25 | F16: =IFERROR((E16-D16)/ABS(D16),"-") -> 0.25 | G16: Gross margin on PS revenue
A17: ── SALES & MARKETING ──
A18: Sales Headcount (AEs) | B18: # | C18: Headcount plan | D18: 8 | E18: 14 | F18: =IFERROR((E18-D18)/ABS(D18),"-") -> 0.75 | G18: Account Executives
A19: Avg AE OTE | B19: $ | C19: Comp bands | D19: 140000 | E19: 145000 | F19: =IFERROR((E19-D19)/ABS(D19),"-") -> 0.035714286 | G19: On-Target Earnings incl. base
A20: Sales Commission Rate | B20: % | C20: Comp plan | D20: 0.1 | E20: 0.1 | F20: =IFERROR((E20-D20)/ABS(D20),"-") -> 0 | G20: % of new bookings
A21: Marketing Spend | B21: $ | C21: Budget | D21: 600000 | E21: 900000 | F21: =IFERROR((E21-D21)/ABS(D21),"-") -> 0.5 | G21: Demand gen + brand + events
A22: Lead-to-Customer Conv. Rate | B22: % | C22: CRM | D22: 0.025 | E22: 0.03 | F22: =IFERROR((E22-D22)/ABS(D22),"-") -> 0.2 | G22: Leads converted to new logos
A23: ── R&D ──
A24: R&D Headcount (Engineers) | B24: # | C24: Headcount plan | D24: 12 | E24: 18 | F24: =IFERROR((E24-D24)/ABS(D24),"-") -> 0.5 | G24: Engineering FTEs
A25: Avg Engineer Cost | B25: $ | C25: HR / comp bands | D25: 130000 | E25: 135000 | F25: =IFERROR((E25-D25)/ABS(D25),"-") -> 0.038461538 | G25: Fully loaded annual cost
A26: R&D Other Costs | B26: $ | C26: Budget | D26: 80000 | E26: 120000 | F26: =IFERROR((E26-D26)/ABS(D26),"-") -> 0.5 | G26: Tools, testing, IP
A27: ── G&A ──
A28: G&A Headcount | B28: # | C28: Headcount plan | D28: 4 | E28: 6 | F28: =IFERROR((E28-D28)/ABS(D28),"-") -> 0.5 | G28: Finance, HR, Legal, Exec
A29: Avg G&A Staff Cost | B29: $ | C29: HR / comp bands | D29: 110000 | E29: 115000 | F29: =IFERROR((E29-D29)/ABS(D29),"-") -> 0.045454545 | G29: Fully loaded annual cost
A30: Legal & Accounting Fees | B30: $ | C30: Invoices | D30: 60000 | E30: 75000 | F30: =IFERROR((E30-D30)/ABS(D30),"-") -> 0.25 | G30: External counsel & audit
A31: Office / Facilities | B31: $ | C31: Lease | D31: 120000 | E31: 130000 | F31: =IFERROR((E31-D31)/ABS(D31),"-") -> 0.083333333 | G31: Rent + utilities + tools
A32: ── BALANCE SHEET / CASH ──
A33: DSO (Days Sales Outstanding) | B33: days | C33: AR aging | D33: 35 | E33: 30 | F33: =IFERROR((E33-D33)/ABS(D33),"-") -> -0.14285714 | G33: Collection efficiency
A34: CapEx (% of Revenue) | B34: % | C34: Budget | D34: 0.02 | E34: 0.015 | F34: =IFERROR((E34-D34)/ABS(D34),"-") -> -0.25 | G34: Hardware, leasehold improv.
A35: Tax Rate | B35: % | C35: Tax advisor | D35: 0.21 | E35: 0.21 | F35: =IFERROR((E35-D35)/ABS(D35),"-") -> 0 | G35: Effective corporate tax rate
A37: Color Legend: 🔵 Blue = Hardcoded Input | ⚫ Black = Formula | 🟢 Green = Cross-sheet link | 🟡 Yellow BG = Key driver to review

Sheet Customer Inputs
A1: Customer-Level Driver Input – Year 1 & Year 2
A2: Customer / Segment | B2: Industry | C2: Year 1 | G2: Year 2 | K2: ARR Y1→Y2 Growth | L2: Churn Risk
C3: ARR ($) | D3: Expansion ($) | E3: Churn ($) | F3: NRR (%) | G3: ARR ($) | H3: Expansion ($) | I3: Churn ($) | J3: NRR (%)
A4: Acme Corp | B4: Manufacturing | C4: 120000 | D4: 8000 | E4: 0 | F4: 0.2 | G4: 132000 | H4: 15000 | I4: 0 | J4: 0.25 | K4: =IFERROR((G4-C4)/ABS(C4),"-") -> 0.1 | L4: Low
A5: BrightTech Inc. | B5: Technology | C5: 84000 | D5: 6000 | E5: 0 | F5: 0.2 | G5: 96000 | H5: 8000 | I5: 0 | J5: 0.25 | K5: =IFERROR((G5-C5)/ABS(C5),"-") -> 0.14285714 | L5: Low
A6: CloudBase GmbH | B6: SaaS / ISV | C6: 60000 | D6: 3000 | E6: 0 | F6: 0.2 | G6: 72000 | H6: 5000 | I6: 0 | J6: 0.25 | K6: =IFERROR((G6-C6)/ABS(C6),"-") -> 0.2 | L6: Low
A7: DataFlow AG | B7: Finance | C7: 48000 | D7: 2400 | E7: 0 | F7: 0.2 | G7: 54000 | H7: 3000 | I7: 4000 | J7: 0.15 | K7: =IFERROR((G7-C7)/ABS(C7),"-") -> 0.125 | L7: High
A8: EcoSystems Ltd. | B8: Energy | C8: 36000 | D8: 1800 | E8: 3600 | F8: 0.15 | G8: 36000 | H8: 2000 | I8: 3000 | J8: 0.2 | K8: =IFERROR((G8-C8)/ABS(C8),"-") -> 0 | L8: High
A9: FutureMed Inc. | B9: Healthcare | C9: 72000 | D9: 5000 | E9: 0 | F9: 0.2 | G9: 84000 | H9: 7000 | I9: 0 | J9: 0.25 | K9: =IFERROR((G9-C9)/ABS(C9),"-") -> 0.16666667 | L9: Low
A10: GrowthOps LLC | B10: Consulting | C10: 24000 | D10: 1000 | E10: 2400 | F10: 0.15 | G10: 24000 | H10: 1200 | I10: 2400 | J10: 0.18 | K10: =IFERROR((G10-C10)/ABS(C10),"-") -> 0 | L10: High
A11: HubSpire SA | B11: Marketing Tech | C11: 96000 | D11: 7000 | E11: 0 | F11: 0.2 | G11: 108000 | H11: 10000 | I11: 0 | J11: 0.25 | K11: =IFERROR((G11-C11)/ABS(C11),"-") -> 0.125 | L11: Low
A12: IntelliCore BV | B12: Manufacturing | C12: 60000 | D12: 4000 | E12: 0 | F12: 0.2 | G12: 72000 | H12: 5000 | I12: 0 | J12: 0.22 | K12: =IFERROR((G12-C12)/ABS(C12),"-") -> 0.2 | L12: Low
A13: JetStream Retail | B13: Retail | C13: 48000 | D13: 2000 | E13: 4800 | F13: 0.15 | G13: 48000 | H13: 2500 | I13: 4800 | J13: 0.18 | K13: =IFERROR((G13-C13)/ABS(C13),"-") -> 0 | L13: High
A14: KeyMetrics GmbH | B14: Analytics | C14: 84000 | D14: 6000 | E14: 0 | F14: 0.2 | G14: 96000 | H14: 8000 | I14: 0 | J14: 0.25 | K14: =IFERROR((G14-C14)/ABS(C14),"-") -> 0.14285714 | L14: Low
A15: LumaCloud Inc. | B15: Technology | C15: 36000 | D15: 1500 | E15: 0 | F15: 0.2 | G15: 42000 | H15: 2000 | I15: 3600 | J15: 0.18 | K15: =IFERROR((G15-C15)/ABS(C15),"-") -> 0.16666667 | L15: High
... A23: TechBridge GmbH | B23: Technology | C23: 72000 | D23: 5000 | E23: 0 | F23: 0.2 | G23: 84000 | H23: 6000 | I23: 0 | J23: 0.25 | K23: =IFERROR((G23-C23)/ABS(C23),"-") -> 0.16666667 | L23: Low
A24: TOTAL | C24: =SUM(C4:C23) -> 1404000 | D24: =SUM(D4:D23) -> 91400 | E24: =SUM(E4:E23) -> 15600 | F24: =IFERROR((E24-D24)/ABS(C24),"-") -> -0.053988604 | G24: =SUM(G4:G23) -> 1602000 | H24: =SUM(H4:H23) -> 128000 | I24: =SUM(I4:I23) -> 28600 | J24: =IFERROR((I24-H24)/ABS(G24),"-") -> -0.062047441 | K24: =IFERROR((G24-C24)/ABS(C24),"-") -> 0.14102564

Sheet P&L
A1: SaaS Income Statement (P&L) – Year 1 & Year 2
A2: Line Item | B2: Unit | C2: Year 1 | D2: % Rev Y1 | E2: Year 2 | F2: % Rev Y2
A3: REVENUE
A4: Subscription Revenue (ARR) | B4: $ | C4: ='Customer Inputs'!C24 -> 1404000 | D4: =IFERROR(C4/C7,"-") -> 0.93887923 | E4: ='Customer Inputs'!G24 -> 1602000 | F4: =IFERROR(E4/E7,"-") -> 0.92601156
A5: Expansion MRR Revenue | B5: $ | C5: ='Customer Inputs'!D24 -> 91400 | D5: =IFERROR(C5/C7,"-") -> 0.06112077 | E5: ='Customer Inputs'!H24 -> 128000 | F5: =IFERROR(E5/E7,"-") -> 0.073988439
A6: Professional Services Revenue | B6: $ | C6: =C3*0.08 -> 0 | D6: =IFERROR(C6/C7,"-") -> 0 | E6: =E3*0.09 -> 0 | F6: =IFERROR(E6/E7,"-") -> 0
A7: TOTAL REVENUE | B7: $ | C7: =SUM(C4:C6) -> 1495400 | D7: =IFERROR(C7/C7,"-") -> 1 | E7: =SUM(E4:E6) -> 1730000 | F7: =IFERROR(E7/E7,"-") -> 1
A8: COST OF GOODS SOLD (COGS)
A9: Hosting / Infrastructure | B9: $ | C9: =C7*0.08 -> 119632 | D9: =IFERROR(C9/C7,"-") -> 0.08 | E9: =E7*0.07 -> 121100 | F9: =IFERROR(E9/E7,"-") -> 0.07
A10: Technical Support (Personnel) | B10: $ | C10: ='Input Mask'!D12*'Input Mask'!D13 -> 0 | D10: =IFERROR(C10/C7,"-") -> 0 | E10: ='Input Mask'!E12*'Input Mask'!E13 -> 0 | F10: =IFERROR(E10/E7,"-") -> 0
A11: Professional Services COGS | B11: $ | C11: =C6*(1-0.22) -> 0 | D11: =IFERROR(C11/C7,"-") -> 0 | E11: =E6*(1-0.25) -> 0 | F11: =IFERROR(E11/E7,"-") -> 0
A12: TOTAL COGS | B12: $ | C12: =SUM(C9:C11) -> 119632 | E12: =SUM(E9:E11) -> 121100
A13: GROSS PROFIT | B13: $ | C13: =C7-C12 -> 1375768 | D13: =IFERROR(C13/C7,"-") -> 0.92 | E13: =E7-E12 -> 1608900 | F13: =IFERROR(E13/E7,"-") -> 0.93
A14: OPERATING EXPENSES (OpEx)
A15: Sales & Marketing | B15: $ | C15: =C7*0.35 -> 523390 | D15: =IFERROR(C15/C7,"-") -> 0.35 | E15: =E7*0.3 -> 519000 | F15: =IFERROR(E15/E7,"-") -> 0.3
A16: Research & Development | B16: $ | C16: =C7*0.2 -> 299080 | D16: =IFERROR(C16/C7,"-") -> 0.2 | E16: =E7*0.18 -> 311400 | F16: =IFERROR(E16/E7,"-") -> 0.18
A17: General & Administrative | B17: $ | C17: =C7*0.12 -> 179448 | D17: =IFERROR(C17/C7,"-") -> 0.12 | E17: =E7*0.1 -> 173000 | F17: =IFERROR(E17/E7,"-") -> 0.1
A18: TOTAL OPEX | B18: $ | C18: =SUM(C15:C17) -> 1001918 | E18: =SUM(E15:E17) -> 1003400
A19: EBITDA | B19: $ | C19: =C13-C18 -> 373850 | D19: =IFERROR(C19/C7,"-") -> 0.25 | E19: =E13-E18 -> 605500 | F19: =IFERROR(E19/E7,"-") -> 0.35
A20: Depreciation & Amortization | B20: $ | C20: =C7*0.02 -> 29908 | D20: =IFERROR(C20/C7,"-") -> 0.02 | E20: =E7*0.015 -> 25950 | F20: =IFERROR(E20/E7,"-") -> 0.015
A21: EBIT (Operating Income) | B21: $ | C21: =C19-C20 -> 343942 | D21: =IFERROR(C21/C7,"-") -> 0.23 | E21: =E19-E20 -> 579550 | F21: =IFERROR(E21/E7,"-") -> 0.335
A22: Interest & Other (Income)/Expense | B22: $ | C22: 50000 | D22: =IFERROR(C22/C7,"-") -> 0.03343587 | E22: 40000 | F22: =IFERROR(E22/E7,"-") -> 0.023121387
A23: EBT (Pre-Tax Income) | B23: $ | C23: =C21-C22 -> 293942 | D23: =IFERROR(C23/C7,"-") -> 0.19656413 | E23: =E21-E22 -> 539550 | F23: =IFERROR(E23/E7,"-") -> 0.31187861
A24: Income Tax (21%) | B24: $ | C24: =MAX(C23*0.21,0) -> 61727.82 | D24: =IFERROR(C24/C7,"-") -> 0.041278467 | E24: =MAX(E23*0.21,0) -> 113305.5 | F24: =IFERROR(E24/E7,"-") -> 0.065494509
A25: NET INCOME / (LOSS) | B25: $ | C25: =C23-C24 -> 232214.18 | D25: =IFERROR(C25/C7,"-") -> 0.15528566 | E25: =E23-E24 -> 426244.5 | F25: =IFERROR(E25/E7,"-") -> 0.2463841

Sheet KPI Dashboard
A1: SaaS KPI Dashboard – Year 1 vs Year 2
B3: Total ARR ($) | F3: Revenue Growth | J3: Gross Margin % | N3: EBITDA Margin
B4: Benchmark: >$1M target | F4: Benchmark: >30% YoY | J4: Benchmark: 70-80%+ | N4: Benchmark: >10%
B5: Year 1 | D5: Year 2 | F5: Year 1 | H5: Year 2 | J5: Year 1 | L5: Year 2 | N5: Year 1 | P5: Year 2
B6: ='P&L'!C4 -> 1404000 | D6: ='P&L'!E4 -> 1602000 | F6: =IFERROR(('P&L'!E7-'P&L'!C7)/ABS('P&L'!C7),"n/a") -> 0.1568811 | H6: "-" | J6: =IFERROR('P&L'!C13/'P&L'!C7,"n/a") -> 0.92 | L6: =IFERROR('P&L'!E13/'P&L'!E7,"n/a") -> 0.93 | N6: =IFERROR('P&L'!C19/'P&L'!C7,"n/a") -> 0.25 | P6: =IFERROR('P&L'!E19/'P&L'!E7,"n/a") -> 0.35
B7: =IFERROR((D6-B6)/ABS(B6),"n/a") -> 0.14102564 | F7: =IFERROR((H6-F6)/ABS(F6),"n/a") -> n/a | J7: =IFERROR((L6-J6)/ABS(J6),"n/a") -> 0.010869565 | N7: =IFERROR((P6-N6)/ABS(N6),"n/a") -> 0.4
B10: NRR (%) | F10: Gross Churn Rate | J10: CAC (Est.) | N10: LTV / CAC
B11: Benchmark: >110% | F11: Benchmark: <8% | J11: Benchmark: <$6k target | N11: Benchmark: >3x
B12: Year 1 | D12: Year 2 | F12: Year 1 | H12: Year 2 | J12: Year 1 | L12: Year 2 | N12: Year 1 | P12: Year 2
B13: ='Input Mask'!D9 -> 0.05 | D13: ='Input Mask'!E9 -> 0.07 | F13: ='Input Mask'!D8 -> 22000 | H13: ='Input Mask'!E8 -> 25000 | J13: =IFERROR('P&L'!C15/MAX('Input Mask'!D3,1),0) -> 523390 | L13: =IFERROR('P&L'!E15/MAX('Input Mask'!E3,1),0) -> 519000 | N13: =IFERROR(('Input Mask'!D5/'Input Mask'!D8)/('P&L'!C15/MAX('Input Mask'!D3,1)),"n/a") -> 1.042157e-08 | P13: =IFERROR(('Input Mask'!E5/'Input Mask'!E8)/('P&L'!E15/MAX('Input Mask'!E3,1)),"n/a") -> 1.3872832e-08
B14: =IFERROR((D13-B13)/ABS(B13),"n/a") -> 0.4 | F14: =IFERROR((H13-F13)/ABS(F13),"n/a") -> 0.13636364 | J14: =IFERROR((L13-J13)/ABS(J13),"n/a") -> -0.0083876268 | N14: =IFERROR((P13-N13)/ABS(N13),"n/a") -> 0.33116532
B18: P&L SUMMARY
B19: Metric | D19: Year 1 ($) | E19: % Rev | F19: Year 2 ($) | G19: % Rev | H19: YoY Δ
B20: Total Revenue | D20: ='P&L'!C7 -> 1495400 | E20: =IFERROR(D20/C20,"-") -> - | F20: ='P&L'!E7 -> 1730000 | G20: =IFERROR(F20/E20,"-") -> - | H20: =IFERROR((F20-D20)/ABS(D20),"-") -> 0.1568811
B21: Gross Profit | D21: ='P&L'!C13 -> 1375768 | E21: =IFERROR(D21/C20,"-") -> - | F21: ='P&L'!E13 -> 1608900 | G21: =IFERROR(F21/E20,"-") -> - | H21: =IFERROR((F21-D21)/ABS(D21),"-") -> 0.1694559
B22: EBITDA | D22: ='P&L'!C19 -> 373850 | E22: =IFERROR(D22/C20,"-") -> - | F22: ='P&L'!E19 -> 605500 | G22: =IFERROR(F22/E20,"-") -> - | H22: =IFERROR((F22-D22)/ABS(D22),"-") -> 0.61963354
B23: Net Income/(Loss) | D23: ='P&L'!C25 -> 232214.18 | E23: =IFERROR(D23/C20,"-") -> - | F23: ='P&L'!E25 -> 426244.5 | G23: =IFERROR(F23/E20,"-") -> - | H23: =IFERROR((F23-D23)/ABS(D23),"-") -> 0.8355662
B26: ARR BRIDGE – Year 1 to Year 2
B27: ARR Component | D27: Amount ($)
B28: Beginning ARR (Y1) | D28: ='Customer Inputs'!C24 -> 1404000
B29: + New Customer ARR | D29: ='Input Mask'!D3*'Input Mask'!D4 -> 0
B30: + Expansion ARR | D30: ='Customer Inputs'!D24 -> 91400
B31: - Churned ARR | D31: =-'Customer Inputs'!E24 -> -15600
B32: = Ending ARR (Y2 target) | D32: ='Customer Inputs'!G24 -> 1602000
B34: 🟢 Green = Cross-sheet formula | 🔵 Blue = Hardcoded input | All $ values in actual USD
